chemplot/__init__.py
chemplot/chemplot.py
chemplot/descriptors.py
chemplot/parameters.py
chemplot/utils.py
chemplot/data/C_1478_CLINTOX_2.csv
chemplot/data/C_1513_BACE_2.csv
chemplot/data/C_2039_BBBP_2.csv
chemplot/data/C_41127_HIV_3.csv
chemplot/data/R_1291_LOGS.csv
chemplot/data/R_1513_BACE.csv
chemplot/data/R_4200_LOGP.csv
chemplot/data/R_642_SAMPL.csv
chemplot/data/R_9982_AQSOLDB.csv
chemplot/tests/__init__.py
chemplot/tests/cluster_test.py
chemplot/tests/conftest.py
chemplot/tests/fromsmiles_test.py
chemplot/tests/interactive_plot_test.py
chemplot/tests/pca_test.py
chemplot/tests/tsne_test.py
chemplot/tests/umap_test.py
chemplot/tests/utils_test.py
chemplot/tests/visualize_plot_test.py
chemplot/tests/test_data/C_1484_CLINTOX_2_erroneous_smiles.csv
chemplot/tests/test_data/C_2039_BBBP_2_erroneous_smiles.csv
chemplot-1.3.1.dist-info/LICENSE
chemplot-1.3.1.dist-info/METADATA
chemplot-1.3.1.dist-info/WHEEL
chemplot-1.3.1.dist-info/top_level.txt
chemplot-1.3.1.dist-info/RECORD
