Metadata-Version: 2.1
Name: chemplot
Version: 1.3.1
Summary: A python library for chemical space visualization.
Author-email: Murat Cihan Sorkun <mcsorkun@gmail.com>, Dajt Mullaj <dajt.mullai@gmail.com>, Jackson Warner Burns <jwburns@mit.edu>
License: BSD
Project-URL: Homepage, https://github.com/mcsorkun/ChemPlot
Classifier: Intended Audience :: Science/Research
Classifier: Intended Audience :: Developers
Classifier: Programming Language :: Python :: 3.8
Classifier: Programming Language :: Python :: 3.9
Classifier: Programming Language :: Python :: 3.10
Classifier: Programming Language :: Python :: 3.11
Classifier: Programming Language :: Python :: 3.12
Classifier: License :: OSI Approved :: BSD License
Classifier: Operating System :: OS Independent
Classifier: Natural Language :: English
Classifier: Topic :: Scientific/Engineering
Requires-Python: >=3.8
License-File: LICENSE
Requires-Dist: pandas
Requires-Dist: numpy
Requires-Dist: matplotlib
Requires-Dist: seaborn
Requires-Dist: umap-learn
Requires-Dist: scikit-learn
Requires-Dist: bokeh<4,>=3
Requires-Dist: scipy
Requires-Dist: rdkit
Requires-Dist: mordredcommunity
Requires-Dist: networkx
Provides-Extra: test
Requires-Dist: pytest; extra == "test"
Requires-Dist: pytest-cov; extra == "test"
